stadv/__init__.py
stadv/__version__.py
stadv/layers.py
stadv/losses.py
stadv/optimization.py
stadv-0.2.1.dist-info/LICENSE
stadv-0.2.1.dist-info/METADATA
stadv-0.2.1.dist-info/WHEEL
stadv-0.2.1.dist-info/top_level.txt
stadv-0.2.1.dist-info/RECORD
