Metadata-Version: 2.1
Name: stadv
Version: 0.2.1
Summary: Spatially Transformed Adversarial Examples with TensorFlow
Home-page: https://github.com/rakutentech/stAdv
Author: Beranger Dumont
Author-email: beranger.dumont@rakuten.com
License: MIT
Project-URL: Documentation, http://stadv.readthedocs.io/en/latest/stadv.html
Project-URL: Source, https://github.com/rakutentech/stAdv
Project-URL: Tracker, https://github.com/rakutentech/stAdv/issues
Keywords: tensorflow adversarial examples CNN deep learning
Platform: UNKNOWN
Classifier: License :: OSI Approved :: MIT License
Classifier: Development Status :: 4 - Beta
Classifier: Intended Audience :: Developers
Classifier: Intended Audience :: Science/Research
Classifier: Topic :: Scientific/Engineering :: Artificial Intelligence
Classifier: Topic :: Scientific/Engineering :: Image Recognition
Classifier: Programming Language :: Python
Classifier: Programming Language :: Python :: 2
Classifier: Programming Language :: Python :: 2.7
Classifier: Programming Language :: Python :: 3
Requires-Python: >=2.7
Requires-Dist: numpy
Requires-Dist: scipy
